proteinbee/__init__.py
proteinbee/motif.py
proteinbee/structure.py
proteinbee-0.1.0.dist-info/METADATA
proteinbee-0.1.0.dist-info/WHEEL
proteinbee-0.1.0.dist-info/entry_points.txt
proteinbee-0.1.0.dist-info/top_level.txt
proteinbee-0.1.0.dist-info/RECORD
