Metadata-Version: 2.4
Name: proteinbee
Version: 0.1.0
Summary: Add your description here
Author-email: bhashyam.anirudh@gmail.com
Requires-Python: >=3.13
Requires-Dist: biotite>=1.3.0
